gnewcash/__init__.py
gnewcash/account.py
gnewcash/commodity.py
gnewcash/enums.py
gnewcash/file_formats/__init__.py
gnewcash/file_formats/base.py
gnewcash/file_formats/gnucash_sqlite.py
gnewcash/file_formats/gnucash_xml.py
gnewcash/file_formats/sqlite_schema.sql
gnewcash/gnucash_file.py
gnewcash/guid_object.py
gnewcash/py.typed
gnewcash/search.py
gnewcash/slot.py
gnewcash/transaction.py
gnewcash/utils.py
gnewcash-1.4.0.dist-info/LICENSE
gnewcash-1.4.0.dist-info/METADATA
gnewcash-1.4.0.dist-info/WHEEL
gnewcash-1.4.0.dist-info/RECORD
